Products.CMFFormController-4.1.3-py2.7-nspkg.pth
Products/CMFFormController/BaseControllerPageTemplate.py
Products/CMFFormController/ControllerBase.py
Products/CMFFormController/ControllerPageTemplate.py
Products/CMFFormController/ControllerPageTemplateFile.py
Products/CMFFormController/ControllerPythonScript.py
Products/CMFFormController/ControllerState.py
Products/CMFFormController/ControllerValidator.py
Products/CMFFormController/FSControllerBase.py
Products/CMFFormController/FSControllerPageTemplate.py
Products/CMFFormController/FSControllerPythonScript.py
Products/CMFFormController/FSControllerValidator.py
Products/CMFFormController/FormAction.py
Products/CMFFormController/FormController.py
Products/CMFFormController/FormValidator.py
Products/CMFFormController/Key.py
Products/CMFFormController/Script.py
Products/CMFFormController/ValidationError.py
Products/CMFFormController/__init__.py
Products/CMFFormController/config.py
Products/CMFFormController/configure.zcml
Products/CMFFormController/globalVars.py
Products/CMFFormController/interfaces.py
Products/CMFFormController/profiles.zcml
Products/CMFFormController/tool.gif
Products/CMFFormController/utils.py
Products/CMFFormController/Actions/BaseFormAction.py
Products/CMFFormController/Actions/IFormAction.py
Products/CMFFormController/Actions/RedirectTo.py
Products/CMFFormController/Actions/RedirectToAction.py
Products/CMFFormController/Actions/TraverseTo.py
Products/CMFFormController/Actions/TraverseToAction.py
Products/CMFFormController/Actions/__init__.py
Products/CMFFormController/exportimport/__init__.py
Products/CMFFormController/exportimport/configure.zcml
Products/CMFFormController/exportimport/controllerpythonscript.py
Products/CMFFormController/exportimport/controllervalidator.py
Products/CMFFormController/exportimport/formcontroller.py
Products/CMFFormController/exportimport/xml/fcExport.xml
Products/CMFFormController/profiles/default/metadata.xml
Products.CMFFormController-4.1.3.dist-info/METADATA
Products.CMFFormController-4.1.3.dist-info/WHEEL
Products.CMFFormController-4.1.3.dist-info/namespace_packages.txt
Products.CMFFormController-4.1.3.dist-info/top_level.txt
Products.CMFFormController-4.1.3.dist-info/RECORD
