Metadata-Version: 2.1
Name: Products.CMFFormController
Version: 4.1.3
Summary: CMFFormController provides a form validation mechanism for CMF.
Home-page: https://pypi.org/project/Products.CMFFormController
Author: Geoff Davis
Author-email: plone-developers@lists.sourceforge.net
License: BSD
Keywords: Zope CMF Plone form validation
Platform: UNKNOWN
Classifier: Development Status :: 6 - Mature
Classifier: Framework :: Plone
Classifier: Framework :: Plone :: 5.2
Classifier: Framework :: Zope2
Classifier: Framework :: Zope :: 4
Classifier: Framework :: Zope :: 5
Classifier: License :: OSI Approved :: BSD License
Classifier: License :: OSI Approved :: Zope Public License
Classifier: Programming Language :: Python
Classifier: Programming Language :: Python :: 2.7
Classifier: Programming Language :: Python :: 3.6
Classifier: Programming Language :: Python :: 3.7
Classifier: Programming Language :: Python :: 3.8
Requires-Dist: setuptools
Requires-Dist: zope.interface
Requires-Dist: zope.structuredtext
Requires-Dist: zope.tales
Requires-Dist: Products.CMFCore
Requires-Dist: Products.GenericSetup (>=1.8.3)
Requires-Dist: Acquisition
Requires-Dist: transaction
Requires-Dist: Zope2 (>=4.0.a2)
Requires-Dist: Products.PythonScripts (>=4.2)
Provides-Extra: test
Requires-Dist: plone.app.testing ; extra == 'test'
Requires-Dist: plone.app.contenttypes ; extra == 'test'
